{
    "header": {
        "name": "header",
        "background": "core('background')",
        "height": "85px",
        "font-size": "1em",
        "z-index": 5,
        "bar": true,
        "absolute": {
            "enabled": false,
            "top-position": 0
        },
        "dark": {
            "enabled": false,
            "background": "color('greyscale', 'grey-6')"
        },
        "fixed": false,
        "sticky": {
            "enabled": false,
            "background": "color('greyscale', 'grey-6')",
            "height": "70px",
            "logo-height": "28px",
            "font-size": "font-size('size-2')"
        },
        "overlay": "overlay",
        "navigation": "navigation"
    }
}